lightsout/__init__.py
lightsout/__main__.py
lightsout/backends.py
lightsout-1.2.0.dist-info/DESCRIPTION.rst
lightsout-1.2.0.dist-info/METADATA
lightsout-1.2.0.dist-info/RECORD
lightsout-1.2.0.dist-info/WHEEL
lightsout-1.2.0.dist-info/entry_points.txt
lightsout-1.2.0.dist-info/metadata.json
lightsout-1.2.0.dist-info/top_level.txt
